{
    "config": {
        "enabled": "true",
        "message": "Temporarily unavailable"
    },
    "Dash": {
        "title": "Subscribe To Unlock",
        "icon": "https://i.imgur.com/jYjyW6s.jpg",
        "main": "https://i.imgur.com/wAR7C4x.gif",
        "first": "https://youtu.be/gPzrqEVtlLs",
        "second": "https://youtu.be/AFkKa28n8VI",
        "first_button": "Subscribe",
        "second_button": "Like"
    },
    "Main": {
        "title": "Subscribe to Unlock",
        "icon": "https://i.imgur.com/jYjyW6s.jpg",
        "main": "https://i.imgur.com/AYqqo4N.jpg",
        "first": "https://youtu.be/bAFGV5-LaLE",
        "second": "https://vt.tiktok.com/ZSLQo67Qo/",
        "first_button": "Comment",
        "second_button": "Like"
    }
}
